infrahouse_core/__init__.py
infrahouse_core/exceptions.py
infrahouse_core/fs.py
infrahouse_core/github.py
infrahouse_core/logging.py
infrahouse_core/timeout.py
infrahouse_core/validation.py
infrahouse_core/aws/__init__.py
infrahouse_core/aws/asg.py
infrahouse_core/aws/asg_instance.py
infrahouse_core/aws/config.py
infrahouse_core/aws/dynamodb.py
infrahouse_core/aws/ec2_instance.py
infrahouse_core/aws/exceptions.py
infrahouse_core/aws/secretsmanager.py
infrahouse_core/aws/route53/__init__.py
infrahouse_core/aws/route53/exceptions.py
infrahouse_core/aws/route53/zone.py
infrahouse_core-0.20.0.dist-info/licenses/AUTHORS.rst
infrahouse_core-0.20.0.dist-info/licenses/LICENSE
infrahouse_core-0.20.0.dist-info/METADATA
infrahouse_core-0.20.0.dist-info/WHEEL
infrahouse_core-0.20.0.dist-info/top_level.txt
infrahouse_core-0.20.0.dist-info/RECORD
